tests/daemon/__init__.py
tools_shared/__init__.py
tools_shared/cmd_line_parser.py
vrc_t70/__init__.py
vrc_t70/__main__.py
vrc_t70/base_communicator.py
vrc_t70/commands.py
vrc_t70/communicator.py
vrc_t70/defaults.py
vrc_t70/error_codes.py
vrc_t70/exceptions.py
vrc_t70/limitations.py
vrc_t70/request.py
vrc_t70/response.py
vrc_t70/command_line/__init__.py
vrc_t70/command_line/find_devices.py
vrc_t70/command_line/get_temperatures.py
vrc_t70/command_line/list_ports.py
vrc_t70/command_line/shared.py
vrc_t70-0.0.1.4.dist-info/LICENSE
vrc_t70-0.0.1.4.dist-info/METADATA
vrc_t70-0.0.1.4.dist-info/WHEEL
vrc_t70-0.0.1.4.dist-info/entry_points.txt
vrc_t70-0.0.1.4.dist-info/top_level.txt
vrc_t70-0.0.1.4.dist-info/RECORD
